{
  "id": 388,
  "name": "Izhikevich Spiking Neuron Model",
  "experiments": [
    {
      "id": 656,
      "aspectConfigurations": [
        
      ],
      "name": "Izhikevich Spiking Neuron Model simulation",
      "description": "Re-implementation of Izhikevich\u2019s spiking neuron model. For more information see http:\/\/opensourcebrain.org\/projects\/izhikevichmodel",
      "lastModified": 1436102517000,
      "status": "COMPLETED",
      "simulationResults": [
        
      ],
      "script": "\/script.js",
      "isPublic": false,
      "view": {
        "id": 417,
        "viewStates": {
          "views": {
            "Popup1": {
              "widgetType": 1,
              "isWidget": true,
              "transparentBackground": false,
              "showHistoryNavigationBar": true,
              "name": "Model Description - Izhikevich Spiking Neuron Network",
              "size": {
                "height": 394,
                "width": 490
              },
              "position": {
                "left": 95,
                "top": 140
              },
              "data": ["Model.neuroml.net1", ["HTMLType"]],
              "componentSpecific": {
                "customHandlers": [
                  {
                    "funct": "function customHandler(node, path, widget) {\n            var n;\n            try {\n                n = eval(path);\n                var metaType = n.getMetaType();\n                if (metaType == GEPPETTO.Resources.VARIABLE_NODE) {\n                    \/\/A plot function inside a channel\n                    G.addWidget(Widgets.PLOT).then(function (w) {\n                        return w.plotFunctionNode(n);\n                    });\n                } else if (metaType == GEPPETTO.Resources.VISUAL_GROUP_NODE) {\n                    \/\/A visual group\n                    n.show(true);\n                } else if (metaType == GEPPETTO.Resources.COMPOSITE_TYPE_NODE) {\n                    \/\/Another composite\n                    widget.setName('Information for ' + n.getId()).setData(n, [GEPPETTO.Resources.HTML_TYPE]);\n                }\n            } catch (ex) {\n                node = undefined;\n            }\n        }",
                    "event": "click"
                  }
                ]
              }
            },
            "Popup2": {
              "widgetType": 1,
              "isWidget": true,
              "transparentBackground": false,
              "name": "Info",
              "size": {
                "height": 160,
                "width": 350
              },
              "position": {
                "left": 1308.5,
                "top": 154.5
              },
              "dataType": "string",
              "data": "Example of set of cells using the  <a target='_blank' href='http:\/\/izhikevich.org\/publications\/whichmod.htm'>Izhikevich spiking neuron model<\/a>.<br\/><br\/> The <b>original OSB project<\/b> for this model is <a target='_blank' href='http:\/\/www.opensourcebrain.org\/projects\/izhikevichmodel'>here<\/a>.",
              "componentSpecific": {
                "customHandlers": [
                  
                ]
              }
            },
            "Tutorial1": {
              "widgetType": "TUTORIAL",
              "isWidget": true,
              "dataType": "array",
              "data": [
                
              ],
              "componentSpecific": {
                "activeTutorial": "Open Source Brain Tutorial",
                "currentStep": 0
              },
              "size": {
                "height": 300,
                "width": 350
              },
              "position": {
                "left": "50%",
                "top": "50%"
              }
            },
            "Tutorial2": {
              "widgetType": "TUTORIAL",
              "isWidget": true,
              "dataType": "array",
              "data": [
                
              ],
              "componentSpecific": {
                "activeTutorial": "Open Source Brain Tutorial",
                "currentStep": 0
              },
              "size": {
                "height": 300,
                "width": 350
              },
              "position": {
                "left": "50%",
                "top": "50%"
              }
            },
            "Console1": {
              "widgetType": "CONSOLE",
              "isWidget": false
            },
            "Canvas1": {
              "widgetType": "CANVAS",
              "isWidget": false,
              "dataType": "instances",
              "data": [
                "izhikevich"
              ],
              "componentSpecific": {
                "cameraPosition": {
                  "x": 110.619,
                  "y": -1.666,
                  "z": 101.74
                },
                "cameraRotation": {
                  "rx": 0.016,
                  "ry": 0.045,
                  "rz": 0.002,
                  "radius": 102.131
                },
                "colorMap": {
                  
                },
                "opacityMap": {
                  
                },
                "geometryTypeMap": {
                  
                },
                "backgroundColor": "0x101010"
              }
            }
          }
        }
      }
    }
  ],
  "activeExperimentId": 656,
  "geppettoModel": {
    "id": 1170,
    "url": "\/GeppettoModel.xmi",
    "type": "GEPPETTO_PROJECT"
  },
  "isPublic": false,
  "isReadOnly": false,
  "view": {
    "id": 418,
    "viewStates": {
      "views": {
        "Canvas1": {
          "widgetType": "CANVAS",
          "componentSpecific": {
            "radiusMap": {
              
            },
            "colorMap": {
              
            }
          }
        }
      }
    }
  }
}
